{
  "associatedLayout": "main_scene",
  "name": "boss_fight",
  "instances": [
    {
      "angle": 0,
      "customSize": true,
      "depth": 1,
      "height": 64,
      "keepRatio": true,
      "layer": "",
      "name": "collision_wall_obj",
      "persistentUuid": "50091a6a-1459-4461-8497-c709810dd59c",
      "width": 1927,
      "x": -2,
      "y": -63,
      "zOrder": 1,
      "numberProperties": [],
      "stringProperties": [],
      "initialVariables": []
    },
    {
      "angle": 0,
      "customSize": true,
      "depth": 1,
      "height": 1098,
      "keepRatio": true,
      "layer": "",
      "name": "collision_wall_obj",
      "persistentUuid": "4646e0b5-00fb-4c9f-882f-253741686d2f",
      "width": 64,
      "x": 1919,
      "y": -1,
      "zOrder": 2,
      "numberProperties": [],
      "stringProperties": [],
      "initialVariables": []
    },
    {
      "angle": 0,
      "customSize": true,
      "depth": 1,
      "height": 64,
      "keepRatio": true,
      "layer": "",
      "name": "collision_wall_obj",
      "persistentUuid": "37f908c3-46ae-472c-be6e-a9e87e78a2b0",
      "width": 1933,
      "x": -9,
      "y": 1074,
      "zOrder": 3,
      "numberProperties": [],
      "stringProperties": [],
      "initialVariables": []
    },
    {
      "angle": 0,
      "customSize": true,
      "depth": 1,
      "height": 1092,
      "keepRatio": true,
      "layer": "",
      "name": "collision_wall_obj",
      "persistentUuid": "f5c5887a-68ce-4e24-b5be-32420b7b6cad",
      "width": 64,
      "x": -59,
      "y": -10,
      "zOrder": 4,
      "numberProperties": [],
      "stringProperties": [],
      "initialVariables": []
    },
    {
      "angle": 0,
      "customSize": false,
      "height": 0,
      "keepRatio": true,
      "layer": "",
      "name": "player_obj",
      "persistentUuid": "544844d3-42ab-4663-9f1b-d44147e46dbd",
      "width": 0,
      "x": 652,
      "y": 505,
      "zOrder": 5,
      "numberProperties": [],
      "stringProperties": [],
      "initialVariables": []
    },
    {
      "angle": 0,
      "customSize": false,
      "height": 0,
      "keepRatio": true,
      "layer": "",
      "name": "boss_obj",
      "persistentUuid": "0e6c85be-db2b-45a0-a1ea-37c6a94b9d6e",
      "width": 0,
      "x": 1110,
      "y": -480,
      "zOrder": 6,
      "numberProperties": [],
      "stringProperties": [],
      "initialVariables": []
    },
    {
      "angle": 0,
      "customSize": false,
      "height": 0,
      "keepRatio": true,
      "layer": "",
      "name": "topl_twn",
      "persistentUuid": "315ec92a-203c-4e39-a62e-4f7ba15a0cfc",
      "width": 0,
      "x": 387,
      "y": 194,
      "zOrder": 7,
      "numberProperties": [],
      "stringProperties": [],
      "initialVariables": []
    },
    {
      "angle": 0,
      "customSize": false,
      "height": 0,
      "keepRatio": true,
      "layer": "",
      "name": "topr_twn",
      "persistentUuid": "d62db50e-8058-427d-ba00-1f60971cca57",
      "width": 0,
      "x": 1505,
      "y": 194,
      "zOrder": 8,
      "numberProperties": [],
      "stringProperties": [],
      "initialVariables": []
    },
    {
      "angle": 0,
      "customSize": false,
      "height": 0,
      "keepRatio": true,
      "layer": "",
      "name": "bottoml_twn",
      "persistentUuid": "08985636-1202-4738-89f6-30c9735f8f54",
      "width": 0,
      "x": 387,
      "y": 803,
      "zOrder": 9,
      "numberProperties": [],
      "stringProperties": [],
      "initialVariables": []
    },
    {
      "angle": 0,
      "customSize": false,
      "height": 0,
      "keepRatio": true,
      "layer": "",
      "name": "bottomr_twn",
      "persistentUuid": "317be78a-63f6-40a4-82f6-6dc57c24a85b",
      "width": 0,
      "x": 1505,
      "y": 803,
      "zOrder": 10,
      "numberProperties": [],
      "stringProperties": [],
      "initialVariables": []
    },
    {
      "angle": 0,
      "customSize": false,
      "height": 0,
      "keepRatio": true,
      "layer": "",
      "name": "center_twn",
      "persistentUuid": "c02f23b7-a29c-46d7-bd3a-6536fc2735ca",
      "width": 0,
      "x": 953,
      "y": 494,
      "zOrder": 11,
      "numberProperties": [],
      "stringProperties": [],
      "initialVariables": []
    }
  ],
  "editionSettings": {
    "grid": false,
    "gridType": "rectangular",
    "gridWidth": 32,
    "gridHeight": 32,
    "gridDepth": 32,
    "gridOffsetX": 0,
    "gridOffsetY": 0,
    "gridOffsetZ": 0,
    "gridColor": 10401023,
    "gridAlpha": 0.8,
    "snap": false,
    "zoomFactor": 0.3645833333333333,
    "windowMask": false,
    "selectedLayer": "",
    "gameEditorMode": "instances-editor"
  }
}
