{
  "associatedLayout": "main_scene",
  "name": "player_controls",
  "events": [
    {
      "type": "BuiltinCommonInstructions::Comment",
      "color": {
        "b": 109,
        "g": 230,
        "r": 255,
        "textB": 0,
        "textG": 0,
        "textR": 0
      },
      "comment": "Movement"
    },
    {
      "type": "BuiltinCommonInstructions::Standard",
      "conditions": [
        {
          "type": {
            "value": "KeyFromTextPressed"
          },
          "parameters": [
            "",
            "\"a\""
          ]
        },
        {
          "type": {
            "value": "BooleanObjectVariable"
          },
          "parameters": [
            "player_obj",
            "able_to_move",
            "True",
            ""
          ]
        },
        {
          "type": {
            "value": "BooleanObjectVariable"
          },
          "parameters": [
            "player_obj",
            "using_spell",
            "False",
            ""
          ]
        },
        {
          "type": {
            "value": "BooleanObjectVariable"
          },
          "parameters": [
            "player_obj",
            "melee_attack",
            "False",
            ""
          ]
        }
      ],
      "actions": [
        {
          "type": {
            "value": "FlippableCapability::FlippableBehavior::FlipX"
          },
          "parameters": [
            "player_obj",
            "Flippable",
            "yes"
          ]
        },
        {
          "type": {
            "value": "AnimatableCapability::AnimatableBehavior::SetName"
          },
          "parameters": [
            "player_obj",
            "Animation",
            "=",
            "\"side\""
          ]
        },
        {
          "type": {
            "value": "AnimatableCapability::AnimatableBehavior::PlayAnimation"
          },
          "parameters": [
            "player_obj",
            "Animation"
          ]
        },
        {
          "type": {
            "value": "SetBooleanObjectVariable"
          },
          "parameters": [
            "player_obj",
            "moving",
            "True",
            ""
          ]
        }
      ],
      "events": [
        {
          "type": "BuiltinCommonInstructions::Standard",
          "conditions": [
            {
              "type": {
                "inverted": true,
                "value": "KeyFromTextPressed"
              },
              "parameters": [
                "",
                "\"LShift\""
              ]
            }
          ],
          "actions": [
            {
              "type": {
                "value": "AddForceXY"
              },
              "parameters": [
                "player_obj",
                "-100",
                "0",
                ""
              ]
            }
          ]
        },
        {
          "type": "BuiltinCommonInstructions::Standard",
          "conditions": [
            {
              "type": {
                "value": "KeyFromTextPressed"
              },
              "parameters": [
                "",
                "\"LShift\""
              ]
            }
          ],
          "actions": [
            {
              "type": {
                "value": "AddForceXY"
              },
              "parameters": [
                "player_obj",
                "-200",
                "0",
                ""
              ]
            }
          ]
        }
      ]
    },
    {
      "type": "BuiltinCommonInstructions::Standard",
      "conditions": [
        {
          "type": {
            "value": "KeyFromTextPressed"
          },
          "parameters": [
            "",
            "\"d\""
          ]
        },
        {
          "type": {
            "value": "BooleanObjectVariable"
          },
          "parameters": [
            "player_obj",
            "able_to_move",
            "True",
            ""
          ]
        },
        {
          "type": {
            "value": "BooleanObjectVariable"
          },
          "parameters": [
            "player_obj",
            "using_spell",
            "False",
            ""
          ]
        },
        {
          "type": {
            "value": "BooleanObjectVariable"
          },
          "parameters": [
            "player_obj",
            "melee_attack",
            "False",
            ""
          ]
        }
      ],
      "actions": [
        {
          "type": {
            "value": "FlippableCapability::FlippableBehavior::FlipX"
          },
          "parameters": [
            "player_obj",
            "Flippable",
            "no"
          ]
        },
        {
          "type": {
            "value": "AnimatableCapability::AnimatableBehavior::SetName"
          },
          "parameters": [
            "player_obj",
            "Animation",
            "=",
            "\"side\""
          ]
        },
        {
          "type": {
            "value": "AnimatableCapability::AnimatableBehavior::PlayAnimation"
          },
          "parameters": [
            "player_obj",
            "Animation"
          ]
        },
        {
          "type": {
            "value": "SetBooleanObjectVariable"
          },
          "parameters": [
            "player_obj",
            "moving",
            "True",
            ""
          ]
        }
      ],
      "events": [
        {
          "type": "BuiltinCommonInstructions::Standard",
          "conditions": [
            {
              "type": {
                "inverted": true,
                "value": "KeyFromTextPressed"
              },
              "parameters": [
                "",
                "\"LShift\""
              ]
            }
          ],
          "actions": [
            {
              "type": {
                "value": "AddForceXY"
              },
              "parameters": [
                "player_obj",
                "100",
                "0",
                ""
              ]
            }
          ]
        },
        {
          "type": "BuiltinCommonInstructions::Standard",
          "conditions": [
            {
              "type": {
                "value": "KeyFromTextPressed"
              },
              "parameters": [
                "",
                "\"LShift\""
              ]
            }
          ],
          "actions": [
            {
              "type": {
                "value": "AddForceXY"
              },
              "parameters": [
                "player_obj",
                "200",
                "0",
                ""
              ]
            }
          ]
        }
      ]
    },
    {
      "type": "BuiltinCommonInstructions::Standard",
      "conditions": [
        {
          "type": {
            "value": "KeyFromTextPressed"
          },
          "parameters": [
            "",
            "\"w\""
          ]
        },
        {
          "type": {
            "value": "BooleanObjectVariable"
          },
          "parameters": [
            "player_obj",
            "able_to_move",
            "True",
            ""
          ]
        },
        {
          "type": {
            "value": "BooleanObjectVariable"
          },
          "parameters": [
            "player_obj",
            "using_spell",
            "False",
            ""
          ]
        },
        {
          "type": {
            "value": "BooleanObjectVariable"
          },
          "parameters": [
            "player_obj",
            "melee_attack",
            "False",
            ""
          ]
        }
      ],
      "actions": [
        {
          "type": {
            "value": "AnimatableCapability::AnimatableBehavior::SetName"
          },
          "parameters": [
            "player_obj",
            "Animation",
            "=",
            "\"Up\""
          ]
        },
        {
          "type": {
            "value": "AnimatableCapability::AnimatableBehavior::PlayAnimation"
          },
          "parameters": [
            "player_obj",
            "Animation"
          ]
        },
        {
          "type": {
            "value": "SetBooleanObjectVariable"
          },
          "parameters": [
            "player_obj",
            "moving",
            "True",
            ""
          ]
        }
      ],
      "events": [
        {
          "type": "BuiltinCommonInstructions::Standard",
          "conditions": [
            {
              "type": {
                "inverted": true,
                "value": "KeyFromTextPressed"
              },
              "parameters": [
                "",
                "\"LShift\""
              ]
            }
          ],
          "actions": [
            {
              "type": {
                "value": "AddForceXY"
              },
              "parameters": [
                "player_obj",
                "0",
                "-100",
                ""
              ]
            }
          ]
        },
        {
          "type": "BuiltinCommonInstructions::Standard",
          "conditions": [
            {
              "type": {
                "value": "KeyFromTextPressed"
              },
              "parameters": [
                "",
                "\"LShift\""
              ]
            }
          ],
          "actions": [
            {
              "type": {
                "value": "AddForceXY"
              },
              "parameters": [
                "player_obj",
                "0",
                "-200",
                ""
              ]
            }
          ]
        }
      ]
    },
    {
      "type": "BuiltinCommonInstructions::Standard",
      "conditions": [
        {
          "type": {
            "value": "KeyFromTextPressed"
          },
          "parameters": [
            "",
            "\"s\""
          ]
        },
        {
          "type": {
            "value": "BooleanObjectVariable"
          },
          "parameters": [
            "player_obj",
            "able_to_move",
            "True",
            ""
          ]
        },
        {
          "type": {
            "value": "BooleanObjectVariable"
          },
          "parameters": [
            "player_obj",
            "using_spell",
            "False",
            ""
          ]
        },
        {
          "type": {
            "value": "BooleanObjectVariable"
          },
          "parameters": [
            "player_obj",
            "melee_attack",
            "False",
            ""
          ]
        }
      ],
      "actions": [
        {
          "type": {
            "value": "AnimatableCapability::AnimatableBehavior::SetName"
          },
          "parameters": [
            "player_obj",
            "Animation",
            "=",
            "\"down\""
          ]
        },
        {
          "type": {
            "value": "AnimatableCapability::AnimatableBehavior::PlayAnimation"
          },
          "parameters": [
            "player_obj",
            "Animation"
          ]
        },
        {
          "type": {
            "value": "SetBooleanObjectVariable"
          },
          "parameters": [
            "player_obj",
            "moving",
            "True",
            ""
          ]
        }
      ],
      "events": [
        {
          "type": "BuiltinCommonInstructions::Standard",
          "conditions": [
            {
              "type": {
                "inverted": true,
                "value": "KeyFromTextPressed"
              },
              "parameters": [
                "",
                "\"LShift\""
              ]
            }
          ],
          "actions": [
            {
              "type": {
                "value": "AddForceXY"
              },
              "parameters": [
                "player_obj",
                "0",
                "100",
                ""
              ]
            }
          ]
        },
        {
          "type": "BuiltinCommonInstructions::Standard",
          "conditions": [
            {
              "type": {
                "value": "KeyFromTextPressed"
              },
              "parameters": [
                "",
                "\"LShift\""
              ]
            }
          ],
          "actions": [
            {
              "type": {
                "value": "AddForceXY"
              },
              "parameters": [
                "player_obj",
                "0",
                "200",
                ""
              ]
            }
          ]
        }
      ]
    },
    {
      "type": "BuiltinCommonInstructions::Standard",
      "conditions": [
        {
          "type": {
            "value": "BooleanObjectVariable"
          },
          "parameters": [
            "player_obj",
            "moving",
            "True",
            ""
          ]
        },
        {
          "type": {
            "value": "BuiltinCommonInstructions::Once"
          },
          "parameters": []
        }
      ],
      "actions": [
        {
          "type": {
            "value": "PlaySoundOnChannel"
          },
          "parameters": [
            "",
            "walking2.mp3",
            "6",
            "yes",
            "20",
            ""
          ]
        }
      ]
    },
    {
      "type": "BuiltinCommonInstructions::Standard",
      "conditions": [
        {
          "type": {
            "value": "BooleanObjectVariable"
          },
          "parameters": [
            "player_obj",
            "moving",
            "False",
            ""
          ]
        }
      ],
      "actions": [
        {
          "type": {
            "value": "PauseSoundChannel"
          },
          "parameters": [
            "",
            "6"
          ]
        }
      ]
    },
    {
      "type": "BuiltinCommonInstructions::Comment",
      "color": {
        "b": 109,
        "g": 230,
        "r": 255,
        "textB": 0,
        "textG": 0,
        "textR": 0
      },
      "comment": "Animation"
    },
    {
      "type": "BuiltinCommonInstructions::Standard",
      "conditions": [
        {
          "type": {
            "inverted": true,
            "value": "AnyKeyPressed"
          },
          "parameters": [
            ""
          ]
        }
      ],
      "actions": [
        {
          "type": {
            "value": "AnimatableCapability::AnimatableBehavior::PauseAnimation"
          },
          "parameters": [
            "player_obj",
            "Animation"
          ]
        },
        {
          "type": {
            "value": "SetBooleanObjectVariable"
          },
          "parameters": [
            "player_obj",
            "moving",
            "False",
            ""
          ]
        }
      ]
    },
    {
      "type": "BuiltinCommonInstructions::Standard",
      "conditions": [
        {
          "type": {
            "inverted": true,
            "value": "AnyKeyPressed"
          },
          "parameters": [
            ""
          ]
        }
      ],
      "actions": [
        {
          "type": {
            "value": "PauseSoundChannel"
          },
          "parameters": [
            "",
            "6"
          ]
        }
      ]
    },
    {
      "type": "BuiltinCommonInstructions::Standard",
      "conditions": [
        {
          "type": {
            "value": "KeyFromTextPressed"
          },
          "parameters": [
            "",
            "\"w\""
          ]
        },
        {
          "type": {
            "value": "KeyFromTextPressed"
          },
          "parameters": [
            "",
            "\"a\""
          ]
        }
      ],
      "actions": [
        {
          "type": {
            "value": "AnimatableCapability::AnimatableBehavior::SetName"
          },
          "parameters": [
            "player_obj",
            "Animation",
            "=",
            "\"Up\""
          ]
        }
      ]
    },
    {
      "type": "BuiltinCommonInstructions::Standard",
      "conditions": [
        {
          "type": {
            "value": "KeyFromTextPressed"
          },
          "parameters": [
            "",
            "\"w\""
          ]
        },
        {
          "type": {
            "value": "KeyFromTextPressed"
          },
          "parameters": [
            "",
            "\"d\""
          ]
        }
      ],
      "actions": [
        {
          "type": {
            "value": "AnimatableCapability::AnimatableBehavior::SetName"
          },
          "parameters": [
            "player_obj",
            "Animation",
            "=",
            "\"Up\""
          ]
        }
      ]
    },
    {
      "type": "BuiltinCommonInstructions::Standard",
      "conditions": [
        {
          "type": {
            "value": "KeyFromTextPressed"
          },
          "parameters": [
            "",
            "\"s\""
          ]
        },
        {
          "type": {
            "value": "KeyFromTextPressed"
          },
          "parameters": [
            "",
            "\"a\""
          ]
        }
      ],
      "actions": [
        {
          "type": {
            "value": "AnimatableCapability::AnimatableBehavior::SetName"
          },
          "parameters": [
            "player_obj",
            "Animation",
            "=",
            "\"down\""
          ]
        }
      ]
    },
    {
      "type": "BuiltinCommonInstructions::Standard",
      "conditions": [
        {
          "type": {
            "value": "KeyFromTextPressed"
          },
          "parameters": [
            "",
            "\"s\""
          ]
        },
        {
          "type": {
            "value": "KeyFromTextPressed"
          },
          "parameters": [
            "",
            "\"d\""
          ]
        }
      ],
      "actions": [
        {
          "type": {
            "value": "AnimatableCapability::AnimatableBehavior::SetName"
          },
          "parameters": [
            "player_obj",
            "Animation",
            "=",
            "\"down\""
          ]
        }
      ]
    },
    {
      "type": "BuiltinCommonInstructions::Comment",
      "color": {
        "b": 109,
        "g": 230,
        "r": 255,
        "textB": 0,
        "textG": 0,
        "textR": 0
      },
      "comment": "Player Position"
    },
    {
      "type": "BuiltinCommonInstructions::Standard",
      "conditions": [
        {
          "type": {
            "value": "SceneJustBegins"
          },
          "parameters": [
            ""
          ]
        }
      ],
      "actions": [
        {
          "type": {
            "value": "SetXY"
          },
          "parameters": [
            "player_obj",
            "=",
            "player_position_x",
            "=",
            "player_position_y"
          ]
        }
      ]
    },
    {
      "type": "BuiltinCommonInstructions::Standard",
      "conditions": [],
      "actions": []
    },
    {
      "type": "BuiltinCommonInstructions::Comment",
      "color": {
        "b": 109,
        "g": 230,
        "r": 255,
        "textB": 0,
        "textG": 0,
        "textR": 0
      },
      "comment": "Dash"
    },
    {
      "type": "BuiltinCommonInstructions::Standard",
      "conditions": [
        {
          "type": {
            "value": "BooleanVariable"
          },
          "parameters": [
            "maze_complete",
            "True",
            "="
          ]
        },
        {
          "type": {
            "value": "KeyFromTextPressed"
          },
          "parameters": [
            "",
            "\"Space\""
          ]
        },
        {
          "type": {
            "value": "KeyFromTextPressed"
          },
          "parameters": [
            "",
            "\"w\""
          ]
        },
        {
          "type": {
            "value": "NumberObjectVariable"
          },
          "parameters": [
            "mana_bar_obj",
            "mana_amount",
            ">=",
            "10"
          ]
        },
        {
          "type": {
            "value": "BuiltinCommonInstructions::Once"
          },
          "parameters": []
        }
      ],
      "actions": [
        {
          "type": {
            "value": "AddForceXY"
          },
          "parameters": [
            "player_obj",
            "0",
            "-3000",
            "0"
          ]
        },
        {
          "type": {
            "value": "SetNumberObjectVariable"
          },
          "parameters": [
            "mana_bar_obj",
            "mana_amount",
            "-",
            "10"
          ]
        }
      ]
    },
    {
      "type": "BuiltinCommonInstructions::Standard",
      "conditions": [
        {
          "type": {
            "value": "BooleanVariable"
          },
          "parameters": [
            "maze_complete",
            "True",
            "="
          ]
        },
        {
          "type": {
            "value": "KeyFromTextPressed"
          },
          "parameters": [
            "",
            "\"Space\""
          ]
        },
        {
          "type": {
            "value": "KeyFromTextPressed"
          },
          "parameters": [
            "",
            "\"a\""
          ]
        },
        {
          "type": {
            "value": "NumberObjectVariable"
          },
          "parameters": [
            "mana_bar_obj",
            "mana_amount",
            ">=",
            "10"
          ]
        },
        {
          "type": {
            "value": "BuiltinCommonInstructions::Once"
          },
          "parameters": []
        }
      ],
      "actions": [
        {
          "type": {
            "value": "AddForceXY"
          },
          "parameters": [
            "player_obj",
            "-3000",
            "0",
            "0"
          ]
        },
        {
          "type": {
            "value": "SetNumberObjectVariable"
          },
          "parameters": [
            "mana_bar_obj",
            "mana_amount",
            "-",
            "10"
          ]
        }
      ]
    },
    {
      "type": "BuiltinCommonInstructions::Standard",
      "conditions": [
        {
          "type": {
            "value": "BooleanVariable"
          },
          "parameters": [
            "maze_complete",
            "True",
            "="
          ]
        },
        {
          "type": {
            "value": "KeyFromTextPressed"
          },
          "parameters": [
            "",
            "\"Space\""
          ]
        },
        {
          "type": {
            "value": "KeyFromTextPressed"
          },
          "parameters": [
            "",
            "\"s\""
          ]
        },
        {
          "type": {
            "value": "NumberObjectVariable"
          },
          "parameters": [
            "mana_bar_obj",
            "mana_amount",
            ">=",
            "10"
          ]
        },
        {
          "type": {
            "value": "BuiltinCommonInstructions::Once"
          },
          "parameters": []
        }
      ],
      "actions": [
        {
          "type": {
            "value": "AddForceXY"
          },
          "parameters": [
            "player_obj",
            "0",
            "3000",
            "0"
          ]
        },
        {
          "type": {
            "value": "SetNumberObjectVariable"
          },
          "parameters": [
            "mana_bar_obj",
            "mana_amount",
            "-",
            "10"
          ]
        }
      ]
    },
    {
      "type": "BuiltinCommonInstructions::Standard",
      "conditions": [
        {
          "type": {
            "value": "BooleanVariable"
          },
          "parameters": [
            "maze_complete",
            "True",
            "="
          ]
        },
        {
          "type": {
            "value": "KeyFromTextPressed"
          },
          "parameters": [
            "",
            "\"Space\""
          ]
        },
        {
          "type": {
            "value": "KeyFromTextPressed"
          },
          "parameters": [
            "",
            "\"d\""
          ]
        },
        {
          "type": {
            "value": "NumberObjectVariable"
          },
          "parameters": [
            "mana_bar_obj",
            "mana_amount",
            ">=",
            "10"
          ]
        },
        {
          "type": {
            "value": "BuiltinCommonInstructions::Once"
          },
          "parameters": []
        }
      ],
      "actions": [
        {
          "type": {
            "value": "AddForceXY"
          },
          "parameters": [
            "player_obj",
            "3000",
            "0",
            "0"
          ]
        },
        {
          "type": {
            "value": "SetNumberObjectVariable"
          },
          "parameters": [
            "mana_bar_obj",
            "mana_amount",
            "-",
            "10"
          ]
        }
      ]
    }
  ]
}
